MANIFEST.in
README.rst
setup.cfg
setup.py
mbq/__init__.py
mbq.client.egg-info/PKG-INFO
mbq.client.egg-info/SOURCES.txt
mbq.client.egg-info/dependency_links.txt
mbq.client.egg-info/not-zip-safe
mbq.client.egg-info/requires.txt
mbq.client.egg-info/top_level.txt
mbq/client/__init__.py
mbq/client/__version__.py
mbq/client/authenticator.py
mbq/client/client.py
mbq/client/exceptions.py
mbq/client/py.typed
mbq/client/storage.py
mbq/client/token_manager.py
mbq/client/contrib/__init__.py
mbq/client/contrib/permissions.py
mbq/client/contrib/tests/__init__.py
mbq/client/contrib/tests/test_permissions.py
mbq/client/lib/__init__.py
mbq/client/lib/auth0.py
mbq/client/tests/__init__.py
mbq/client/tests/test_client.py
mbq/client/tests/test_storage.py
mbq/client/tests/test_token_manager.py