Metadata-Version: 2.1
Name: mbq.client
Version: 1.2.2
Summary: MBQ Service Client
Home-page: https://github.com/managedbyq/mbq.client
Author: Managed by Q, Inc.
Author-email: open-source@managedbyq.com
Maintainer: Managed by Q, Inc.
Maintainer-email: open-source@managedbyq.com
License: Apache 2.0
Keywords: token access authorization
Platform: UNKNOWN
Classifier: Development Status :: 4 - Beta
Classifier: Intended Audience :: Developers
Classifier: License :: OSI Approved :: Apache Software License
Classifier: Operating System :: OS Independent
Classifier: Programming Language :: Python :: 3
Classifier: Programming Language :: Python :: 3.6
Classifier: Programming Language :: Python :: 3.7
Classifier: Topic :: Software Development :: Libraries
